cpanbd/__init__.py
cpanbd/baiduTo123.py
cpanbd/downfile.py
cpanbd/file.py
cpanbd/upload.py
cpanbd/uploadfile.py
cpanbd/user.py
cpanbd/apijson/__init__.py
cpanbd/apijson/file.json
cpanbd/apijson/upload.json
cpanbd/apijson/user.json
cpanbd/utils/__init__.py
cpanbd/utils/api.py
cpanbd/utils/auth.py
cpanbd/utils/baseapiclient.py
cpanbd/utils/checkdata.py
cpanbd/utils/const.py
cpanbd/utils/core.py
cpanbd/utils/download.py
cpanbd/utils/md5.py
cpanbd-0.1.1.dist-info/METADATA
cpanbd-0.1.1.dist-info/WHEEL
cpanbd-0.1.1.dist-info/entry_points.txt
cpanbd-0.1.1.dist-info/RECORD
