Metadata-Version: 2.4
Name: cpanbd
Version: 0.1.1
Summary: 百度云盘的python接口文档(非官方)
Project-URL: Homepage, https://github.com/zoushucai/cpanbd
Project-URL: Documentation, https://cpanbd.readthedocs.org
Project-URL: Repository, https://github.com/zoushucai/cpanbd.git
Project-URL: Issues, https://github.com/zoushucai/cpanbd/issues
Project-URL: Changelog, https://github.com/zoushucai/cpanbd/blob/main/CHANGELOG.md
Author-email: zoushucai <zoushucai@users.noreply.github.com>
Requires-Python: >=3.10
Requires-Dist: json5>=0.10.0
Requires-Dist: jsonpath>=0.6.0
Requires-Dist: pydantic>=2.1.0
Requires-Dist: python-dotenv>=1.1.0
Requires-Dist: requests>=2.10.0
Requires-Dist: tenacity>=8.0.0
Requires-Dist: tqdm>=4.0.0
